packtest/__init__.py
packtest/codepackage.py
pack_test-0.1.0.dist-info/LICENSE
pack_test-0.1.0.dist-info/METADATA
pack_test-0.1.0.dist-info/WHEEL
pack_test-0.1.0.dist-info/top_level.txt
pack_test-0.1.0.dist-info/RECORD
