Metadata-Version: 2.1
Name: pack-test
Version: 0.1.0
Summary: Test suite enhancement for testing plugins
Home-page: https://github.com/turnbullerin/packtest
Author: Erin Turnbull
Author-email: erin.a.turnbull@gmail.com
Project-URL: Bug Tracker, https://github.com/turnbullerin/packtest/issues
Classifier: Programming Language :: Python :: 3
Classifier: License :: OSI Approved :: MIT License
Classifier: Operating System :: OS Independent
Requires-Python: >=3.7
License-File: LICENSE
